README.rst
setup.py
Flask_CloudflareRemote.egg-info/PKG-INFO
Flask_CloudflareRemote.egg-info/SOURCES.txt
Flask_CloudflareRemote.egg-info/dependency_links.txt
Flask_CloudflareRemote.egg-info/not-zip-safe
Flask_CloudflareRemote.egg-info/requires.txt
Flask_CloudflareRemote.egg-info/top_level.txt
flask_cloudflare_remote/__init__.py
flask_cloudflare_remote/remote.py
flask_cloudflare_remote/version.py