Metadata-Version: 1.1
Name: Flask-CloudflareRemote
Version: 1.1.0
Summary: Cloudflare proxy support for flask application
Home-page: https://github.com/cs91chris/flask_cloudflare_remote
Author: cs91chris
Author-email: cs91chris@voidbrain.me
License: MIT
Platform: any
Classifier: Environment :: Web Environment
Classifier: Intended Audience :: Developers
Classifier: License :: OSI Approved :: MIT License
Classifier: Operating System :: OS Independent
Classifier: Programming Language :: Python :: 3
Classifier: Topic :: Internet :: WWW/HTTP :: Dynamic Content
Classifier: Topic :: Software Development :: Libraries :: Python Modules
